ai_council/__init__.py
ai_council/config.py
ai_council/logger.py
ai_council/main.py
ai_council/models.py
ai_council/synthesis.py
ai_council-0.2.3.dist-info/METADATA
ai_council-0.2.3.dist-info/WHEEL
ai_council-0.2.3.dist-info/entry_points.txt
ai_council-0.2.3.dist-info/licenses/LICENSE
ai_council-0.2.3.dist-info/RECORD
