Metadata-Version: 2.4
Name: ai-council
Version: 0.2.3
Summary: Multi-AI consensus tool: MCP server that queries multiple AI models (OpenAI, Claude, Gemini, custom APIs) in parallel, synthesizes responses for better accuracy, and reduces AI bias through ensemble decision-making
Project-URL: Homepage, https://github.com/0xAkuti/ai-council-mcp
Project-URL: Repository, https://github.com/0xAkuti/ai-council-mcp
Project-URL: Issues, https://github.com/0xAkuti/ai-council-mcp/issues
Author-email: Akuti <a40723201+0xAkuti@users.noreply.github.com>
License: MIT License
License-File: LICENSE
Keywords: ai-aggregation,ai-api,ai-assistant,ai-automation,ai-benchmarking,ai-collaboration,ai-comparison,ai-consensus,ai-council,ai-evaluation,ai-middleware,ai-pipeline,ai-proxy,ai-research,ai-synthesis,ai-tools,ai-validation,anthropic,api-aggregation,async,bias-reduction,chatbot,claude,claude-desktop,cognition-wheel,concurrent,cursor-ai,decision-support,expert-system,gemini,gpt,llm-api,llm-evaluation,llm-orchestration,mcp,mcp-server,model-context-protocol,model-ensemble,model-fusion,multi-llm,
Classifier: Development Status :: 4 - Beta
Classifier: Intended Audience :: Developers
Classifier: License :: OSI Approved :: MIT License
Classifier: Programming Language :: Python :: 3
Classifier: Programming Language :: Python :: 3.10
Classifier: Programming Language :: Python :: 3.11
Classifier: Programming Language :: Python :: 3.12
Classifier: Programming Language :: Python :: 3.13
Requires-Python: >=3.10
Requires-Dist: httpx>=0.28.1
Requires-Dist: mcp>=1.9.4
Requires-Dist: openai>=1.91.0
Requires-Dist: pydantic-settings>=2.10.1
Requires-Dist: pydantic>=2.11.7
Requires-Dist: pyyaml>=6.0.2
